benchmarks/__init__.py
benchmarks/cmp_NA19240.py
benchmarks/eval_BND.py
benchmarks/eval_forcecalling.py
benchmarks/eval_sim.py
benchmarks/eval_trio.py
benchmarks/multi_platform.py
benchmarks/sta_venn.py
benchmarks/vcf2bedpe.py
cuteFC/CommandRunner.py
cuteFC/__init__.py
cuteFC/cuteSV_Description.py
cuteFC/cuteSV_forcecalling.py
cuteFC/cuteSV_genotype.py
cuteFC/cuteSV_resolveDUP.py
cuteFC/cuteSV_resolveINDEL.py
cuteFC/cuteSV_resolveINV.py
cuteFC/cuteSV_resolveTRA.py
cuteFC/diploid_calling.py
cuteFC-1.0.0.data/data/LICENSE
cuteFC-1.0.0.data/scripts/cuteFC
cuteFC-1.0.0.dist-info/LICENSE
cuteFC-1.0.0.dist-info/METADATA
cuteFC-1.0.0.dist-info/WHEEL
cuteFC-1.0.0.dist-info/top_level.txt
cuteFC-1.0.0.dist-info/RECORD
