Metadata-Version: 2.1
Name: cuteFC
Version: 1.0.0
Summary: Regenotyping structural variants through an accurate and efficient force-calling method
Home-page: https://github.com/tjiangHIT/cuteFC
Author: Jiang Tao & Cao Shuqi
Author-email: tjiang@hit.edu.cn
License: MIT
License-File: LICENSE
Requires-Dist: scipy
Requires-Dist: pysam
Requires-Dist: Biopython
Requires-Dist: Cigar
Requires-Dist: numpy
Requires-Dist: pyvcf3
Requires-Dist: scikit-learn
